{
  "train_stats": {
    "best_loss": 0.14858761055883007,
    "best_epoch": 0,
    "early_stop_tracker": 0,
    "cur_epoch": 0,
    "train_acc": [
      0.9122613072395325
    ],
    "train_loss": [
      0.46612693479920303
    ],
    "val_acc": [
      0.9695571660995483
    ],
    "val_loss": [
      0.14858761055883007
    ]
  },
  "model_params": {
    "type": "cnn",
    "img_size": [
      1,
      28,
      28
    ],
    "nf": 1,
    "n_classes": 2
  },
  "args": {
    "data_dir": "C:/Users/afons/Documents/2023-2024/tese/gasten_timeSeries/data",
    "out_dir": "C:/Users/afons/Documents/2023-2024/tese/gasten_timeSeries/models",
    "name": null,
    "dataset_name": "mnist",
    "pos_class": 7,
    "neg_class": 1,
    "batch_size": 64,
    "c_type": "cnn",
    "epochs": 1,
    "early_stop": 3,
    "lr": 0.001,
    "nf": 1,
    "seed": 26504,
    "device": "cpu"
  }
}